entity_linker/__init__.py
entity_linker-0.0.1.dist-info/METADATA
entity_linker-0.0.1.dist-info/WHEEL
entity_linker-0.0.1.dist-info/top_level.txt
entity_linker-0.0.1.dist-info/RECORD
