Metadata-Version: 2.1
Name: entity-linker
Version: 0.0.1
Summary: Entity linker
Author-email: Ikuya Yamada <ikuya@ikuya.net>
Classifier: Programming Language :: Python :: 3
Classifier: License :: OSI Approved :: MIT License
Classifier: Operating System :: OS Independent
Requires-Python: >=3.8
